tox_passenv/__init__.py
tox_passenv/_tox4_plugin.py
tox_passenv/plugin.py
tox_passenv/version.py
tox_passenv-0.1.0.dist-info/LICENSE
tox_passenv-0.1.0.dist-info/METADATA
tox_passenv-0.1.0.dist-info/WHEEL
tox_passenv-0.1.0.dist-info/entry_points.txt
tox_passenv-0.1.0.dist-info/top_level.txt
tox_passenv-0.1.0.dist-info/RECORD
